kraft/__init__.py
kraft/__main__.py
kraft/addon_manager.py
kraft/cli.py
kraft/renderer.py
kraft/ui.py
kraft/validators.py
kraft/addons/__init__.py
kraft/addons/postgres/addon.yml
kraft/addons/postgres/database.py.jinja
kraft/addons/postgres/models_db.py.jinja
kraft/addons/postgres/readme-section.md.jinja
kraft/addons/postgres/routes_db.py.jinja
kraft/templates/rest/.env.example
kraft/templates/rest/.gitignore
kraft/templates/rest/.kraft.yml.jinja
kraft/templates/rest/Dockerfile.jinja
kraft/templates/rest/LICENSE
kraft/templates/rest/README.md.jinja
kraft/templates/rest/docker-compose.yml.jinja
kraft/templates/rest/pyproject.toml.jinja
kraft/templates/rest/template.yml
kraft/templates/rest/src/{{package_name}}/__init__.py
kraft/templates/rest/src/{{package_name}}/main.py.jinja
kraft/templates/rest/src/{{package_name}}/models.py.jinja
kraft/templates/rest/src/{{package_name}}/routes.py.jinja
kraft/templates/rest/tests/__init__.py
kraft/templates/rest/tests/test_api.py.jinja
kraft_cli-0.2.1.dist-info/METADATA
kraft_cli-0.2.1.dist-info/WHEEL
kraft_cli-0.2.1.dist-info/entry_points.txt
kraft_cli-0.2.1.dist-info/RECORD
