Metadata-Version: 2.4
Name: kraft-cli
Version: 0.2.1
Summary: Python service scaffolding with zero learning curve
Author-email: kraft <kraft@example.com>
License: MIT
Requires-Python: >=3.10
Requires-Dist: jinja2>=3.1.0
Requires-Dist: pyyaml>=6.0.0
Requires-Dist: rich>=13.0.0
Requires-Dist: typer>=0.9.0
Provides-Extra: dev
Requires-Dist: hypothesis>=6.92.0; extra == 'dev'
Requires-Dist: mypy>=1.7.0; extra == 'dev'
Requires-Dist: pytest>=7.4.0; extra == 'dev'
Requires-Dist: ruff>=0.1.0; extra == 'dev'
